oauthmanager/.config/creds_config.json
oauthmanager/.config/creds_config.md
oauthmanager/.config/env.example
oauthmanager/__init__.py
oauthmanager/cli.py
oauthmanager/core.py
oauthmanager/providers/__init__.py
oauthmanager/providers/base.py
oauthmanager/providers/googleDrive/__init__.py
oauthmanager/providers/googleDrive/drive.py
oauthmanager/providers/spotify/__init__.py
oauthmanager/providers/spotify/spotify.py
oauthmanager/vaults/listVaults.py
oauthmanager/vaults/onepassword.py
oauthmanager/vaults/vaults.json
oauthmanager-0.1.12.dist-info/LICENSE
oauthmanager-0.1.12.dist-info/METADATA
oauthmanager-0.1.12.dist-info/WHEEL
oauthmanager-0.1.12.dist-info/entry_points.txt
oauthmanager-0.1.12.dist-info/RECORD
