Metadata-Version: 2.1
Name: oauthmanager
Version: 0.1.12
Summary: A module for managing API authentication using 1Password and more.
License: MIT
Author: Suhail
Author-email: suhailece@gmail.com
Requires-Python: >=3.11,<4.0
Classifier: License :: OSI Approved :: MIT License
Classifier: Programming Language :: Python :: 3
Classifier: Programming Language :: Python :: 3.11
Classifier: Programming Language :: Python :: 3.12
Classifier: Programming Language :: Python :: 3.13
Requires-Dist: click (>=8.2.1,<9.0.0)
Requires-Dist: cryptography (>=43.0.1,<44.0.0)
Requires-Dist: google-api-python-client (>=2.170.0,<3.0.0)
Requires-Dist: google-auth-httplib2 (>=0.2.0,<0.3.0)
Requires-Dist: google-auth-oauthlib (>=1.2.2,<2.0.0)
Requires-Dist: spotipy (>=2.25,<3.0)
